<game_config>
  <game_key>rust_linux64</game_key>
  <protocol>gameq</protocol>
  <gameq_query_name>rust</gameq_query_name>
  <installer>steamcmd</installer>
  <game_name>Rust</game_name>
  <server_exec_name>RustDedicatedOGP.sh</server_exec_name>
  <query_port type="add">1</query_port>
  <cli_template>-batchmode %IP% %PORT% %PLAYERS% %HOSTNAME% %IDENTITY% %WORLD_SIZE% %SEED% %SALT% %TICKRATE% %SAVEINTERNAL% %SECURE% %RCONWEB% +rcon.ip "0.0.0.0" %QUERY_PORT% %CONTROL_PASSWORD% -logfile RustDedicated_Data/output_log.txt</cli_template>
  <cli_params>
    <cli_param id="IP" cli_string="+server.ip" options="sq" />
    <cli_param id="PORT" cli_string="+server.port" options="sq" />
    <cli_param id="PLAYERS" cli_string="+server.maxplayers" options="sq" />
    <cli_param id="HOSTNAME" cli_string="+server.hostname" options="sq" />
    <cli_param id="QUERY_PORT" cli_string="+rcon.port" options="sq" />
    <cli_param id="CONTROL_PASSWORD" cli_string="+rcon.password" options="sq" />
  </cli_params>
  <console_log>RustDedicated_Data/output_log.txt</console_log>
  <max_user_amount>500</max_user_amount>
  <mods>
    <mod key="rust">
      <name>none</name>
      <installer_name>258550</installer_name>
      <installer_login>anonymous</installer_login>
      <betaname>experimental</betaname>
    </mod>
  </mods>
  <server_params>
    <param key="+server.identity" type="text" id="IDENTITY">
      <default>my_server_identity</default>
      <caption></caption>
      <desc>Changes path to your server data rust/server/my_server_identity.</desc>
    </param>
    <param key="+server.worldsize" type="text" id="WORLD_SIZE">
      <default>3000</default>
      <caption></caption>
      <desc>Defines the size of the map generated (min 2000, max 8000).</desc>
    </param>
    <param key="+server.seed" type="text" id="SEED">
      <default>0</default>
      <caption></caption>
      <desc>Defines the map generation seed (min 0, max 429497295).</desc>
    </param>
    <param key="+server.salt" type="text" id="SALT">
      <default>0</default>
      <caption></caption>
      <desc>Defines the randomization to mining resources.</desc>
    </param>
    <param key="+server.tickrate" type="text" id="TICKRATE">
      <default>30</default>
      <caption></caption>
      <desc>Server refresh rate (min acceptable 15, max 100) - Increasing this value increase CPU usage.</desc>
    </param>
    <!-- Removing this for now because server will start on Bootstrap non-map where you can't spawn if this parameter is defined
      <param key="+server.level" type="select" id="MAP">
      <option value="Procedural Map">Procedural Map</option>
      <option value="HapisIsland">Hapis Island</option>
      <option value="SavasIsland">Savas Island</option>
      <option value="Barren">Barren</option>
      <caption></caption>
      <desc>The map to start on (Hapis Island doesn't support seed and salt).</desc>
    </param> -->
    <param key="+server.saveinterval" type="text" id="SAVEINTERNAL">
      <default>600</default>
      <caption></caption>
      <desc>Time in seconds for server save.</desc>
    </param>
    <param key="+server.secure" type="select" id="SECURE">
      <option value="true">Enabled</option>
      <option value="false">Disabled</option>
      <caption></caption>
      <desc>VAC and EAC secured.</desc>
    </param>
    <param key="+rcon.web" type="select" id="RCONWEB">
      <option value="0">Disabled</option>
      <option value="1">Enabled</option>
      <caption></caption>
      <desc>If set to enabled, use websocket rcon. If set to disabled, use legacy source engine rcon.</desc>
    </param>
  </server_params>
  <post_install>
		echo &apos;#!/bin/bash
		export LD_LIBRARY_PATH="./RustDedicated_Data/Plugins/x86_64"
		./RustDedicated $@&apos; &gt; RustDedicatedOGP.sh
		chmod +x RustDedicatedOGP.sh
   </post_install>
</game_config>
